gartic_room.py
gartic_room-0.0.3.dist-info/LICENSE
gartic_room-0.0.3.dist-info/METADATA
gartic_room-0.0.3.dist-info/WHEEL
gartic_room-0.0.3.dist-info/RECORD
